tenacity_error_feedback/__init__.py
tenacity_error_feedback/core.py
tenacity_error_feedback-0.1.0.dist-info/licenses/LICENSE
tenacity_error_feedback-0.1.0.dist-info/METADATA
tenacity_error_feedback-0.1.0.dist-info/WHEEL
tenacity_error_feedback-0.1.0.dist-info/top_level.txt
tenacity_error_feedback-0.1.0.dist-info/RECORD
