Metadata-Version: 2.4
Name: tenacity-error-feedback
Version: 0.1.0
Summary: Propagate error context between tenacity retry attempts
Author: Bohan Qu
License: MIT
Project-URL: Homepage, https://github.com/LastRemote/tenacity-error-feedback
Project-URL: Bug Tracker, https://github.com/LastRemote/tenacity-error-feedback/issues
Classifier: Programming Language :: Python :: 3
Classifier: Programming Language :: Python :: 3.7
Classifier: Programming Language :: Python :: 3.8
Classifier: Programming Language :: Python :: 3.9
Classifier: Programming Language :: Python :: 3.10
Classifier: Programming Language :: Python :: 3.11
Classifier: Programming Language :: Python :: 3.12
Classifier: Programming Language :: Python :: 3.13
Classifier: License :: OSI Approved :: MIT License
Classifier: Operating System :: OS Independent
Requires-Python: >=3.7
License-File: LICENSE
Requires-Dist: tenacity>=8.0.0
Dynamic: license-file
